tinyscaf/__init__.py
tinyscaf/tinyscaf.py
tinyscaf/util/__init__.py
tinyscaf/util/logging_config.py
tinyscaf-0.0.2.dist-info/LICENSE
tinyscaf-0.0.2.dist-info/METADATA
tinyscaf-0.0.2.dist-info/WHEEL
tinyscaf-0.0.2.dist-info/entry_points.txt
tinyscaf-0.0.2.dist-info/RECORD
