Metadata-Version: 2.1
Name: tinyscaf
Version: 0.0.2
Summary: A tiny app to scafold individual files.
Author: Marcus Robb
Author-email: marcus.robb@initworx.com
Requires-Python: >=3.12,<4.0
Classifier: Programming Language :: Python :: 3
Classifier: Programming Language :: Python :: 3.12
Requires-Dist: Jinja2 (>=3.1.3,<4.0.0)
Requires-Dist: colorama (>=0.4.6,<0.5.0)
